ecell4_base.cpython-37m-x86_64-linux-gnu.so
ecell4_base-2.1.0.dist-info/AUTHORS
ecell4_base-2.1.0.dist-info/LICENSE
ecell4_base-2.1.0.dist-info/METADATA
ecell4_base-2.1.0.dist-info/WHEEL
ecell4_base-2.1.0.dist-info/top_level.txt
ecell4_base-2.1.0.dist-info/RECORD
ecell4_base.libs/libhdf5-80963a0e.so.103.1.0
ecell4_base.libs/libhdf5_cpp-e9bd8d6d.so.103.1.0
ecell4_base.libs/libgslcblas-31001fd9.so.0.0.0
ecell4_base.libs/libz-eb09ad1d.so.1.2.3
ecell4_base.libs/libgsl-d937a686.so.25.0.0
