Metadata-Version: 2.1
Name: ecell4-base
Version: 2.1.0
Summary: A software platform for modeling, simulation and analysis of complex, heterogeneous and multi-scale systems like the cell. E-Cell has multi-algorithm, multi-timescale and multi-spatial-representation as its central feature.
Home-page: https://github.com/ecell/ecell4_base
Author: Kazunari Kaizu
Author-email: kaizu@riken.jp
License: the GNU General Public License v2
Platform: UNKNOWN
